iverilog/classifier.v
module classifier (
    input [31:0] rms,
    output reg [1:0] fault
);

always @(*) begin
    if (rms < 100000)
        fault = 2'b00; // Healthy
    else if (rms < 200000)
        fault = 2'b01; // Bearing
    else if (rms < 300000)
        fault = 2'b10; // Rotor
    else
        fault = 2'b11; // Stator
end
endmodule

iverilog/feature_extract.v
module feature_extract (
    input clk,
    input rst,
    input signed [15:0] signal,
    output reg [31:0] rms
);

reg [31:0] sum_sq;
reg [9:0] count;

always @(posedge clk) begin
    if (rst) begin
        sum_sq <= 0;
        count <= 0;
        rms <= 0;
    end else begin
        sum_sq <= sum_sq + (signal * signal);
        count <= count + 1;

        if (count == 1023) begin
            rms <= sum_sq >> 10; // approx RMS
            sum_sq <= 0;
            count <= 0;
        end
    end
end
endmodule

iverilog/motor_signal.v
module motor_signal (
    input clk,
    input rst,
    input [1:0] mode,
    output reg signed [15:0] signal
);

reg signed [15:0] sine_lut [0:15];
reg [3:0] idx;

initial begin
    sine_lut[0]=0;   sine_lut[1]=383;
    sine_lut[2]=707; sine_lut[3]=923;
    sine_lut[4]=1000;sine_lut[5]=923;
    sine_lut[6]=707; sine_lut[7]=383;
    sine_lut[8]=0;   sine_lut[9]=-383;
    sine_lut[10]=-707; sine_lut[11]=-923;
    sine_lut[12]=-1000;sine_lut[13]=-923;
    sine_lut[14]=-707; sine_lut[15]=-383;
end

always @(posedge clk) begin
    if (rst) begin
        idx <= 0;
        signal <= 0;
    end else begin
        idx <= idx + 1;

        case (mode)
            2'b00: signal <= sine_lut[idx];           // Healthy
            2'b01: signal <= sine_lut[idx] + 200;     // Bearing
            2'b10: signal <= sine_lut[idx] + (idx*20);// Rotor
            2'b11: signal <= sine_lut[idx] - 300;     // Stator
        endcase
    end
end
endmodule

iverilog/tb_motor_fault.v
module tb_motor_fault;

reg clk;
reg rst;
reg [1:0] mode;

wire signed [15:0] signal;
wire [31:0] rms;
wire [1:0] fault;

motor_signal U1(.clk(clk), .rst(rst), .mode(mode), .signal(signal));
feature_extract U2(.clk(clk), .rst(rst), .signal(signal), .rms(rms));
classifier U3(.rms(rms), .fault(fault));

always #5 clk = ~clk;

initial begin
    // INITIALIZE EVERYTHING
    clk  = 0;
    rst  = 1;
    mode = 2'b00;

    $dumpfile("motor.vcd");
    $dumpvars(0, tb_motor_fault);

    // HOLD RESET PROPERLY
    #50;
    rst = 0;

    // APPLY MODES SLOWLY
    #2000 mode = 2'b00;  // Healthy
    #2000 mode = 2'b01;  // Bearing
    #2000 mode = 2'b10;  // Rotor
    #2000 mode = 2'b11;  // Stator

    #2000 $finish;
end

endmodule


//iverilog tb_motor_fault.v motor_signal.v feature_extract.v classifier.v
// vvp a.out
// gtkwave motor.vcd

iverilog/motor.vcd
$date
	Mon Jan 12 14:09:46 2026
$end
$version
	Icarus Verilog
$end
$timescale
	1s
$end
$scope module tb_motor_fault $end
$var wire 16 ! signal [15:0] $end
$var wire 32 " rms [31:0] $end
$var wire 2 # fault [1:0] $end
$var reg 1 $ clk $end
$var reg 2 % mode [1:0] $end
$var reg 1 & rst $end
$scope module U1 $end
$var wire 1 $ clk $end
$var wire 2 ' mode [1:0] $end
$var wire 1 & rst $end
$var reg 4 ( idx [3:0] $end
$var reg 16 ) signal [15:0] $end
$upscope $end
$scope module U2 $end
$var wire 1 $ clk $end
$var wire 1 & rst $end
$var wire 16 * signal [15:0] $end
$var reg 10 + count [9:0] $end
$var reg 32 , rms [31:0] $end
$var reg 32 - sum_sq [31:0] $end
$upscope $end
$scope module U3 $end
$var wire 32 . rms [31:0] $end
$var reg 2 / fault [1:0] $end
$upscope $end
$upscope $end
$enddefinitions $end
$comment Show the parameter values. $end
$dumpall
$end
#0
$dumpvars
bx /
bx .
bx -
bx ,
bx +
bx *
bx )
bx (
b0 '
1&
b0 %
0$
bx #
bx "
bx !
$end
#5
b0 #
b0 /
b0 !
b0 )
b0 *
b0 (
b0 "
b0 ,
b0 .
b0 +
b0 -
1$
#10
0$
#15
1$
#20
0$
#25
1$
#30
0$
#35
1$
#40
0$
#45
1$
#50
0$
0&
#55
b1 +
b1 (
1$
#60
0$
#65
b101111111 !
b101111111 )
b101111111 *
b10 (
b10 +
1$
#70
0$
#75
b11 +
b100011110100000001 -
b1011000011 !
b1011000011 )
b1011000011 *
b11 (
1$
#80
0$
#85
b1110011011 !
b1110011011 )
b1110011011 *
b100 (
b100 +
b10011101110110001010 -
1$
#90
0$
#95
b101 +
b101101101110101100011 -
b1111101000 !
b1111101000 )
b1111101000 *
b101 (
1$
#100
0$
#105
b1110011011 !
b1110011011 )
b1110011011 *
b110 (
b110 +
b1001100001111110100011 -
1$
#110
0$
#115
b111 +
b1100110001111101111100 -
b1011000011 !
b1011000011 )
b1011000011 *
b111 (
1$
#120
0$
#125
b101111111 !
b101111111 )
b101111111 *
b1000 (
b1000 +
b1110101100000000000101 -
1$
#130
0$
#135
b1001 +
b1111001111110100000110 -
b0 !
b0 )
b0 *
b1001 (
1$
#140
0$
#145
b1111111010000001 !
b1111111010000001 )
b1111111010000001 *
b1010 (
b1010 +
1$
#150
0$
#155
b1011 +
b11111101010000010011101000000111 -
b1111110100111101 !
b1111110100111101 )
b1111110100111101 *
b1011 (
1$
#160
0$
#165
b1111110001100101 !
b1111110001100101 )
b1111110001100101 *
b1100 (
b1100 +
b11110111110000101101101010010000 -
1$
#170
0$
#175
b1101 +
b11110000100110011101101001101001 -
b1111110000011000 !
b1111110000011000 )
b1111110000011000 *
b1101 (
1$
#180
0$
#185
b1111110001100101 !
b1111110001100101 )
b1111110001100101 *
b1110 (
b1110 +
b11101000110110010001110010101001 -
1$
#190
0$
#195
b1111 +
b11100001101100000001110010000010 -
b1111110100111101 !
b1111110100111101 )
b1111110100111101 *
b1111 (
1$
#200
0$
#205
b1111111010000001 !
b1111111010000001 )
b1111111010000001 *
b0 (
b10000 +
b11011100001100011011110100001011 -
1$
#210
0$
#215
b10001 +
b11011001001101011111101000001100 -
b0 !
b0 )
b0 *
b1 (
1$
#220
0$
#225
b101111111 !
b101111111 )
b101111111 *
b10 (
b10010 +
1$
#230
0$
#235
b10011 +
b11011001001110000011011100001101 -
b1011000011 !
b1011000011 )
b1011000011 *
b11 (
1$
#240
0$
#245
b1110011011 !
b1110011011 )
b1110011011 *
b100 (
b10100 +
b11011001001111111101011110010110 -
1$
#250
0$
#255
b10101 +
b11011001010011001101011101101111 -
b1111101000 !
b1111101000 )
b1111101000 *
b101 (
1$
#260
0$
#265
b1110011011 !
b1110011011 )
b1110011011 *
b110 (
b10110 +
b11011001010111000001100110101111 -
1$
#270
0$
#275
b10111 +
b11011001011010010001100110001000 -
b1011000011 !
b1011000011 )
b1011000011 *
b111 (
1$
#280
0$
#285
b101111111 !
b101111111 )
b101111111 *
b1000 (
b11000 +
b11011001011100001011101000010001 -
1$
#290
0$
#295
b11001 +
b11011001011100101111011100010010 -
b0 !
b0 )
b0 *
b1001 (
1$
#300
0$
#305
b1111111010000001 !
b1111111010000001 )
b1111111010000001 *
b1010 (
b11010 +
1$
#310
0$
#315
b11011 +
b11010110011101110011010000010011 -
b1111110100111101 !
b1111110100111101 )
b1111110100111101 *
b1011 (
1$
#320
0$
#325
b1111110001100101 !
b1111110001100101 )
b1111110001100101 *
b1100 (
b11100 +
b11010000111110001101010010011100 -
1$
#330
0$
#335
b11101 +
b11001001110011111101010001110101 -
b1111110000011000 !
b1111110000011000 )
b1111110000011000 *
b1101 (
1$
#340
0$
#345
b1111110001100101 !
b1111110001100101 )
b1111110001100101 *
b1110 (
b11110 +
b11000010000011110001011010110101 -
1$
#350
0$
#355
b11111 +
b10111010111001100001011010001110 -
b1111110100111101 !
b1111110100111101 )
b1111110100111101 *
b1111 (
1$
#360
0$
#365
b1111111010000001 !
b1111111010000001 )
b1111111010000001 *
b0 (
b100000 +
b10110101011001111011011100010111 -
1$
#370
0$
#375
b100001 +
b10110010011010111111010000011000 -
b0 !
b0 )
b0 *
b1 (
1$
#380
0$
#385
b101111111 !
b101111111 )
b101111111 *
b10 (
b100010 +
1$
#390
0$
#395
b100011 +
b10110010011011100011000100011001 -
b1011000011 !
b1011000011 )
b1011000011 *
b11 (
1$
#400
0$
#405
b1110011011 !
b1110011011 )
b1110011011 *
b100 (
b100100 +
b10110010011101011101000110100010 -
1$
#410
0$
#415
b100101 +
b10110010100000101101000101111011 -
b1111101000 !
b1111101000 )
b1111101000 *
b101 (
1$
#420
0$
#425
b1110011011 !
b1110011011 )
b1110011011 *
b110 (
b100110 +
b10110010100100100001001110111011 -
1$
#430
0$
#435
b100111 +
b10110010100111110001001110010100 -
b1011000011 !
b1011000011 )
b1011000011 *
b111 (
1$
#440
0$
#445
b101111111 !
b101111111 )
b101111111 *
b1000 (
b101000 +
b10110010101001101011010000011101 -
1$
#450
0$
#455
b101001 +
b10110010101010001111000100011110 -
b0 !
b0 )
b0 *
b1001 (
1$
#460
0$
#465
b1111111010000001 !
b1111111010000001 )
b1111111010000001 *
b1010 (
b101010 +
1$
#470
0$
#475
b101011 +
b10101111101011010010111000011111 -
b1111110100111101 !
b1111110100111101 )
b1111110100111101 *
b1011 (
1$
#480
0$
#485
b1111110001100101 !
b1111110001100101 )
b1111110001100101 *
b1100 (
b101100 +
b10101010001011101100111010101000 -
1$
#490
0$
#495
b101101 +
b10100011000001011100111010000001 -
b1111110000011000 !
b1111110000011000 )
b1111110000011000 *
b1101 (
1$
#500
0$
#505
b1111110001100101 !
b1111110001100101 )
b1111110001100101 *
b1110 (
b101110 +
b10011011010001010001000011000001 -
1$
#510
0$
#515
b101111 +
b10010100000111000001000010011010 -
b1111110100111101 !
b1111110100111101 )
b1111110100111101 *
b1111 (
1$
#520
0$
#525
b1111111010000001 !
b1111111010000001 )
b1111111010000001 *
b0 (
b110000 +
b10001110100111011011000100100011 -
1$
#530
0$
#535
b110001 +
b10001011101000011110111000100100 -
b0 !
b0 )
b0 *
b1 (
1$
#540
0$
#545
b101111111 !
b101111111 )
b101111111 *
b10 (
b110010 +
1$
#550
0$
#555
b110011 +
b10001011101001000010101100100101 -
b1011000011 !
b1011000011 )
b1011000011 *
b11 (
1$
#560
0$
#565
b1110011011 !
b1110011011 )
b1110011011 *
b100 (
b110100 +
b10001011101010111100101110101110 -
1$
#570
0$
#575
b110101 +
b10001011101110001100101110000111 -
b1111101000 !
b1111101000 )
b1111101000 *
b101 (
1$
#580
0$
#585
b1110011011 !
b1110011011 )
b1110011011 *
b110 (
b110110 +
b10001011110010000000110111000111 -
1$
#590
0$
#595
b110111 +
b10001011110101010000110110100000 -
b1011000011 !
b1011000011 )
b1011000011 *
b111 (
1$
#600
0$
#605
b101111111 !
b101111111 )
b101111111 *
b1000 (
b111000 +
b10001011110111001010111000101001 -
1$
#610
0$
#615
b111001 +
b10001011110111101110101100101010 -
b0 !
b0 )
b0 *
b1001 (
1$
#620
0$
#625
b1111111010000001 !
b1111111010000001 )
b1111111010000001 *
b1010 (
b111010 +
1$
#630
0$
#635
b111011 +
b10001000111000110010100000101011 -
b1111110100111101 !
b1111110100111101 )
b1111110100111101 *
b1011 (
1$
#640
0$
#645
b1111110001100101 !
b1111110001100101 )
b1111110001100101 *
b1100 (
b111100 +
b10000011011001001100100010110100 -
1$
#650
0$
#655
b111101 +
b1111100001110111100100010001101 -
b1111110000011000 !
b1111110000011000 )
b1111110000011000 *
b1101 (
1$
#660
0$
#665
b1111110001100101 !
b1111110001100101 )
b1111110001100101 *
b1110 (
b111110 +
b1110100011110110000101011001101 -
1$
#670
0$
#675
b111111 +
b1101101010100100000101010100110 -
b1111110100111101 !
b1111110100111101 )
b1111110100111101 *
b1111 (
1$
#680
0$
#685
b1111111010000001 !
b1111111010000001 )
b1111111010000001 *
b0 (
b1000000 +
b1100111110100111010101100101111 -
1$
#690
0$
#695
b1000001 +
b1100100110101111110100000110000 -
b0 !
b0 )
b0 *
b1 (
1$
#700
0$
#705
b101111111 !
b101111111 )
b101111111 *
b10 (
b1000010 +
1$
#710
0$
#715
b1000011 +
b1100100110110100010010100110001 -
b1011000011 !
b1011000011 )
b1011000011 *
b11 (
1$
#720
0$
#725
b1110011011 !
b1110011011 )
b1110011011 *
b100 (
b1000100 +
b1100100111000011100010110111010 -
1$
#730
0$
#735
b1000101 +
b1100100111011101100010110010011 -
b1111101000 !
b1111101000 )
b1111101000 *
b101 (
1$
#740
0$
#745
b1110011011 !
b1110011011 )
b1110011011 *
b110 (
b1000110 +
b1100100111111100000011111010011 -
1$
#750
0$
#755
b1000111 +
b1100101000010110000011110101100 -
b1011000011 !
b1011000011 )
b1011000011 *
b111 (
1$
#760
0$
#765
b101111111 !
b101111111 )
b101111111 *
b1000 (
b1001000 +
b1100101000100101010100000110101 -
1$
#770
0$
#775
b1001001 +
b1100101000101001110010100110110 -
b0 !
b0 )
b0 *
b1001 (
1$
#780
0$
#785
b1111111010000001 !
b1111111010000001 )
b1111111010000001 *
b1010 (
b1001010 +
1$
#790
0$
#795
b1001011 +
b1100010000110010010001000110111 -
b1111110100111101 !
b1111110100111101 )
b1111110100111101 *
b1011 (
1$
#800
0$
#805
b1111110001100101 !
b1111110001100101 )
b1111110001100101 *
b1100 (
b1001100 +
b1011100100110101100001011000000 -
1$
#810
0$
#815
b1001101 +
b1010101011100011100001010011001 -
b1111110000011000 !
b1111110000011000 )
b1111110000011000 *
b1101 (
1$
#820
0$
#825
b1111110001100101 !
b1111110001100101 )
b1111110001100101 *
b1110 (
b1001110 +
b1001101101100010000010011011001 -
1$
#830
0$
#835
b1001111 +
b1000110100010000000010010110010 -
b1111110100111101 !
b1111110100111101 )
b1111110100111101 *
b1111 (
1$
#840
0$
#845
b1111111010000001 !
b1111111010000001 )
b1111111010000001 *
b0 (
b1010000 +
b1000001000010011010010100111011 -
1$
#850
0$
#855
b1010001 +
b111110000011011110001000111100 -
b0 !
b0 )
b0 *
b1 (
1$
#860
0$
#865
b101111111 !
b101111111 )
b101111111 *
b10 (
b1010010 +
1$
#870
0$
#875
b1010011 +
b111110000100000001111100111101 -
b1011000011 !
b1011000011 )
b1011000011 *
b11 (
1$
#880
0$
#885
b1110011011 !
b1110011011 )
b1110011011 *
b100 (
b1010100 +
b111110000101111011111111000110 -
1$
#890
0$
#895
b1010101 +
b111110001001001011111110011111 -
b1111101000 !
b1111101000 )
b1111101000 *
b101 (
1$
#900
0$
#905
b1110011011 !
b1110011011 )
b1110011011 *
b110 (
b1010110 +
b111110001101000000000111011111 -
1$
#910
0$
#915
b1010111 +
b111110010000010000000110111000 -
b1011000011 !
b1011000011 )
b1011000011 *
b111 (
1$
#920
0$
#925
b101111111 !
b101111111 )
b101111111 *
b1000 (
b1011000 +
b111110010010001010001001000001 -
1$
#930
0$
#935
b1011001 +
b111110010010101101111101000010 -
b0 !
b0 )
b0 *
b1001 (
1$
#940
0$
#945
b1111111010000001 !
b1111111010000001 )
b1111111010000001 *
b1010 (
b1011010 +
1$
#950
0$
#955
b1011011 +
b111011010011110001110001000011 -
b1111110100111101 !
b1111110100111101 )
b1111110100111101 *
b1011 (
1$
#960
0$
#965
b1111110001100101 !
b1111110001100101 )
b1111110001100101 *
b1100 (
b1011100 +
b110101110100001011110011001100 -
1$
#970
0$
#975
b1011101 +
b101110101001111011110010100101 -
b1111110000011000 !
b1111110000011000 )
b1111110000011000 *
b1101 (
1$
#980
0$
#985
b1111110001100101 !
b1111110001100101 )
b1111110001100101 *
b1110 (
b1011110 +
b100110111001101111111011100101 -
1$
#990
0$
#995
b1011111 +
b11111101111011111111010111110 -
b1111110100111101 !
b1111110100111101 )
b1111110100111101 *
b1111 (
1$
#1000
0$
#1005
b1111111010000001 !
b1111111010000001 )
b1111111010000001 *
b0 (
b1100000 +
b11010001111111001111101000111 -
1$
#1010
0$
#1015
b1100001 +
b10111010000111101110001001000 -
b0 !
b0 )
b0 *
b1 (
1$
#1020
0$
#1025
b101111111 !
b101111111 )
b101111111 *
b10 (
b1100010 +
1$
#1030
0$
#1035
b1100011 +
b10111010001100001100101001001 -
b1011000011 !
b1011000011 )
b1011000011 *
b11 (
1$
#1040
0$
#1045
b1110011011 !
b1110011011 )
b1110011011 *
b100 (
b1100100 +
b10111010011011011100111010010 -
1$
#1050
0$
#1055
b1100101 +
b10111010110101011100110101011 -
b1111101000 !
b1111101000 )
b1111101000 *
b101 (
1$
#1060
0$
#1065
b1110011011 !
b1110011011 )
b1110011011 *
b110 (
b1100110 +
b10111011010011111101111101011 -
1$
#1070
0$
#1075
b1100111 +
b10111011101101111101111000100 -
b1011000011 !
b1011000011 )
b1011000011 *
b111 (
1$
#1080
0$
#1085
b101111111 !
b101111111 )
b101111111 *
b1000 (
b1101000 +
b10111011111101001110001001101 -
1$
#1090
0$
#1095
b1101001 +
b10111100000001101100101001110 -
b0 !
b0 )
b0 *
b1001 (
1$
#1100
0$
#1105
b1111111010000001 !
b1111111010000001 )
b1111111010000001 *
b1010 (
b1101010 +
1$
#1110
0$
#1115
b1101011 +
b10100100001010001011001001111 -
b1111110100111101 !
b1111110100111101 )
b1111110100111101 *
b1011 (
1$
#1120
0$
#1125
b1111110001100101 !
b1111110001100101 )
b1111110001100101 *
b1100 (
b1101100 +
b1111000001101011011011011000 -
1$
#1130
0$
#1135
b1101101 +
b111110111011011011010110001 -
b1111110000011000 !
b1111110000011000 )
b1111110000011000 *
b1101 (
1$
#1140
0$
#1145
b1111110001100101 !
b1111110001100101 )
b1111110001100101 *
b1110 (
b1101110 +
b111001111100011110001 -
1$
#1150
0$
#1155
b1101111 +
b11111000111100111111100011001010 -
b1111110100111101 !
b1111110100111101 )
b1111110100111101 *
b1111 (
1$
#1160
0$
#1165
b1111111010000001 !
b1111111010000001 )
b1111111010000001 *
b0 (
b1110000 +
b11110011011101011001100101010011 -
1$
#1170
0$
#1175
b1110001 +
b11110000011110011101011001010100 -
b0 !
b0 )
b0 *
b1 (
1$
#1180
0$
#1185
b101111111 !
b101111111 )
b101111111 *
b10 (
b1110010 +
1$
#1190
0$
#1195
b1110011 +
b11110000011111000001001101010101 -
b1011000011 !
b1011000011 )
b1011000011 *
b11 (
1$
#1200
0$
#1205
b1110011011 !
b1110011011 )
b1110011011 *
b100 (
b1110100 +
b11110000100000111011001111011110 -
1$
#1210
0$
#1215
b1110101 +
b11110000100100001011001110110111 -
b1111101000 !
b1111101000 )
b1111101000 *
b101 (
1$
#1220
0$
#1225
b1110011011 !
b1110011011 )
b1110011011 *
b110 (
b1110110 +
b11110000100111111111010111110111 -
1$
#1230
0$
#1235
b1110111 +
b11110000101011001111010111010000 -
b1011000011 !
b1011000011 )
b1011000011 *
b111 (
1$
#1240
0$
#1245
b101111111 !
b101111111 )
b101111111 *
b1000 (
b1111000 +
b11110000101101001001011001011001 -
1$
#1250
0$
#1255
b1111001 +
b11110000101101101101001101011010 -
b0 !
b0 )
b0 *
b1001 (
1$
#1260
0$
#1265
b1111111010000001 !
b1111111010000001 )
b1111111010000001 *
b1010 (
b1111010 +
1$
#1270
0$
#1275
b1111011 +
b11101101101110110001000001011011 -
b1111110100111101 !
b1111110100111101 )
b1111110100111101 *
b1011 (
1$
#1280
0$
#1285
b1111110001100101 !
b1111110001100101 )
b1111110001100101 *
b1100 (
b1111100 +
b11101000001111001011000011100100 -
1$
#1290
0$
#1295
b1111101 +
b11100001000100111011000010111101 -
b1111110000011000 !
b1111110000011000 )
b1111110000011000 *
b1101 (
1$
#1300
0$
#1305
b1111110001100101 !
b1111110001100101 )
b1111110001100101 *
b1110 (
b1111110 +
b11011001010100101111001011111101 -
1$
#1310
0$
#1315
b1111111 +
b11010010001010011111001011010110 -
b1111110100111101 !
b1111110100111101 )
b1111110100111101 *
b1111 (
1$
#1320
0$
#1325
b1111111010000001 !
b1111111010000001 )
b1111111010000001 *
b0 (
b10000000 +
b11001100101010111001001101011111 -
1$
#1330
0$
#1335
b10000001 +
b11001001101011111101000001100000 -
b0 !
b0 )
b0 *
b1 (
1$
#1340
0$
#1345
b101111111 !
b101111111 )
b101111111 *
b10 (
b10000010 +
1$
#1350
0$
#1355
b10000011 +
b11001001101100100000110101100001 -
b1011000011 !
b1011000011 )
b1011000011 *
b11 (
1$
#1360
0$
#1365
b1110011011 !
b1110011011 )
b1110011011 *
b100 (
b10000100 +
b11001001101110011010110111101010 -
1$
#1370
0$
#1375
b10000101 +
b11001001110001101010110111000011 -
b1111101000 !
b1111101000 )
b1111101000 *
b101 (
1$
#1380
0$
#1385
b1110011011 !
b1110011011 )
b1110011011 *
b110 (
b10000110 +
b11001001110101011111000000000011 -
1$
#1390
0$
#1395
b10000111 +
b11001001111000101110111111011100 -
b1011000011 !
b1011000011 )
b1011000011 *
b111 (
1$
#1400
0$
#1405
b101111111 !
b101111111 )
b101111111 *
b1000 (
b10001000 +
b11001001111010101001000001100101 -
1$
#1410
0$
#1415
b10001001 +
b11001001111011001100110101100110 -
b0 !
b0 )
b0 *
b1001 (
1$
#1420
0$
#1425
b1111111010000001 !
b1111111010000001 )
b1111111010000001 *
b1010 (
b10001010 +
1$
#1430
0$
#1435
b10001011 +
b11000110111100010000101001100111 -
b1111110100111101 !
b1111110100111101 )
b1111110100111101 *
b1011 (
1$
#1440
0$
#1445
b1111110001100101 !
b1111110001100101 )
b1111110001100101 *
b1100 (
b10001100 +
b11000001011100101010101011110000 -
1$
#1450
0$
#1455
b10001101 +
b10111010010010011010101011001001 -
b1111110000011000 !
b1111110000011000 )
b1111110000011000 *
b1101 (
1$
#1460
0$
#1465
b1111110001100101 !
b1111110001100101 )
b1111110001100101 *
b1110 (
b10001110 +
b10110010100010001110110100001001 -
1$
#1470
0$
#1475
b10001111 +
b10101011010111111110110011100010 -
b1111110100111101 !
b1111110100111101 )
b1111110100111101 *
b1111 (
1$
#1480
0$
#1485
b1111111010000001 !
b1111111010000001 )
b1111111010000001 *
b0 (
b10010000 +
b10100101111000011000110101101011 -
1$
#1490
0$
#1495
b10010001 +
b10100010111001011100101001101100 -
b0 !
b0 )
b0 *
b1 (
1$
#1500
0$
#1505
b101111111 !
b101111111 )
b101111111 *
b10 (
b10010010 +
1$
#1510
0$
#1515
b10010011 +
b10100010111010000000011101101101 -
b1011000011 !
b1011000011 )
b1011000011 *
b11 (
1$
#1520
0$
#1525
b1110011011 !
b1110011011 )
b1110011011 *
b100 (
b10010100 +
b10100010111011111010011111110110 -
1$
#1530
0$
#1535
b10010101 +
b10100010111111001010011111001111 -
b1111101000 !
b1111101000 )
b1111101000 *
b101 (
1$
#1540
0$
#1545
b1110011011 !
b1110011011 )
b1110011011 *
b110 (
b10010110 +
b10100011000010111110101000001111 -
1$
#1550
0$
#1555
b10010111 +
b10100011000110001110100111101000 -
b1011000011 !
b1011000011 )
b1011000011 *
b111 (
1$
#1560
0$
#1565
b101111111 !
b101111111 )
b101111111 *
b1000 (
b10011000 +
b10100011001000001000101001110001 -
1$
#1570
0$
#1575
b10011001 +
b10100011001000101100011101110010 -
b0 !
b0 )
b0 *
b1001 (
1$
#1580
0$
#1585
b1111111010000001 !
b1111111010000001 )
b1111111010000001 *
b1010 (
b10011010 +
1$
#1590
0$
#1595
b10011011 +
b10100000001001110000010001110011 -
b1111110100111101 !
b1111110100111101 )
b1111110100111101 *
b1011 (
1$
#1600
0$
#1605
b1111110001100101 !
b1111110001100101 )
b1111110001100101 *
b1100 (
b10011100 +
b10011010101010001010010011111100 -
1$
#1610
0$
#1615
b10011101 +
b10010011011111111010010011010101 -
b1111110000011000 !
b1111110000011000 )
b1111110000011000 *
b1101 (
1$
#1620
0$
#1625
b1111110001100101 !
b1111110001100101 )
b1111110001100101 *
b1110 (
b10011110 +
b10001011101111101110011100010101 -
1$
#1630
0$
#1635
b10011111 +
b10000100100101011110011011101110 -
b1111110100111101 !
b1111110100111101 )
b1111110100111101 *
b1111 (
1$
#1640
0$
#1645
b1111111010000001 !
b1111111010000001 )
b1111111010000001 *
b0 (
b10100000 +
b1111111000101111000011101110111 -
1$
#1650
0$
#1655
b10100001 +
b1111100000110111100010001111000 -
b0 !
b0 )
b0 *
b1 (
1$
#1660
0$
#1665
b101111111 !
b101111111 )
b101111111 *
b10 (
b10100010 +
1$
#1670
0$
#1675
b10100011 +
b1111100000111100000000101111001 -
b1011000011 !
b1011000011 )
b1011000011 *
b11 (
1$
#1680
0$
#1685
b1110011011 !
b1110011011 )
b1110011011 *
b100 (
b10100100 +
b1111100001001011010001000000010 -
1$
#1690
0$
#1695
b10100101 +
b1111100001100101010000111011011 -
b1111101000 !
b1111101000 )
b1111101000 *
b101 (
1$
#1700
0$
#1705
b1110011011 !
b1110011011 )
b1110011011 *
b110 (
b10100110 +
b1111100010000011110010000011011 -
1$
#1710
0$
#1715
b10100111 +
b1111100010011101110001111110100 -
b1011000011 !
b1011000011 )
b1011000011 *
b111 (
1$
#1720
0$
#1725
b101111111 !
b101111111 )
b101111111 *
b1000 (
b10101000 +
b1111100010101101000010001111101 -
1$
#1730
0$
#1735
b10101001 +
b1111100010110001100000101111110 -
b0 !
b0 )
b0 *
b1001 (
1$
#1740
0$
#1745
b1111111010000001 !
b1111111010000001 )
b1111111010000001 *
b1010 (
b10101010 +
1$
#1750
0$
#1755
b10101011 +
b1111001010111001111111001111111 -
b1111110100111101 !
b1111110100111101 )
b1111110100111101 *
b1011 (
1$
#1760
0$
#1765
b1111110001100101 !
b1111110001100101 )
b1111110001100101 *
b1100 (
b10101100 +
b1110011110111101001111100001000 -
1$
#1770
0$
#1775
b10101101 +
b1101100101101011001111011100001 -
b1111110000011000 !
b1111110000011000 )
b1111110000011000 *
b1101 (
1$
#1780
0$
#1785
b1111110001100101 !
b1111110001100101 )
b1111110001100101 *
b1110 (
b10101110 +
b1100100111101001110000100100001 -
1$
#1790
0$
#1795
b10101111 +
b1011101110010111110000011111010 -
b1111110100111101 !
b1111110100111101 )
b1111110100111101 *
b1111 (
1$
#1800
0$
#1805
b1111111010000001 !
b1111111010000001 )
b1111111010000001 *
b0 (
b10110000 +
b1011000010011011000000110000011 -
1$
#1810
0$
#1815
b10110001 +
b1010101010100011011111010000100 -
b0 !
b0 )
b0 *
b1 (
1$
#1820
0$
#1825
b101111111 !
b101111111 )
b101111111 *
b10 (
b10110010 +
1$
#1830
0$
#1835
b10110011 +
b1010101010100111111101110000101 -
b1011000011 !
b1011000011 )
b1011000011 *
b11 (
1$
#1840
0$
#1845
b1110011011 !
b1110011011 )
b1110011011 *
b100 (
b10110100 +
b1010101010110111001110000001110 -
1$
#1850
0$
#1855
b10110101 +
b1010101011010001001101111100111 -
b1111101000 !
b1111101000 )
b1111101000 *
b101 (
1$
#1860
0$
#1865
b1110011011 !
b1110011011 )
b1110011011 *
b110 (
b10110110 +
b1010101011101111101111000100111 -
1$
#1870
0$
#1875
b10110111 +
b1010101100001001101111000000000 -
b1011000011 !
b1011000011 )
b1011000011 *
b111 (
1$
#1880
0$
#1885
b101111111 !
b101111111 )
b101111111 *
b1000 (
b10111000 +
b1010101100011000111111010001001 -
1$
#1890
0$
#1895
b10111001 +
b1010101100011101011101110001010 -
b0 !
b0 )
b0 *
b1001 (
1$
#1900
0$
#1905
b1111111010000001 !
b1111111010000001 )
b1111111010000001 *
b1010 (
b10111010 +
1$
#1910
0$
#1915
b10111011 +
b1010010100100101111100010001011 -
b1111110100111101 !
b1111110100111101 )
b1111110100111101 *
b1011 (
1$
#1920
0$
#1925
b1111110001100101 !
b1111110001100101 )
b1111110001100101 *
b1100 (
b10111100 +
b1001101000101001001100100010100 -
1$
#1930
0$
#1935
b10111101 +
b1000101111010111001100011101101 -
b1111110000011000 !
b1111110000011000 )
b1111110000011000 *
b1101 (
1$
#1940
0$
#1945
b1111110001100101 !
b1111110001100101 )
b1111110001100101 *
b1110 (
b10111110 +
b111110001010101101101100101101 -
1$
#1950
0$
#1955
b10111111 +
b110111000000011101101100000110 -
b1111110100111101 !
b1111110100111101 )
b1111110100111101 *
b1111 (
1$
#1960
0$
#1965
b1111111010000001 !
b1111111010000001 )
b1111111010000001 *
b0 (
b11000000 +
b110001100000110111101110001111 -
1$
#1970
0$
#1975
b11000001 +
b101110100001111011100010010000 -
b0 !
b0 )
b0 *
b1 (
1$
#1980
0$
#1985
b101111111 !
b101111111 )
b101111111 *
b10 (
b11000010 +
1$
#1990
0$
#1995
b11000011 +
b101110100010011111010110010001 -
b1011000011 !
b1011000011 )
b1011000011 *
b11 (
1$
#2000
0$
#2005
b1110011011 !
b1110011011 )
b1110011011 *
b100 (
b11000100 +
b101110100100011001011000011010 -
1$
#2010
0$
#2015
b11000101 +
b101110100111101001010111110011 -
b1111101000 !
b1111101000 )
b1111101000 *
b101 (
1$
#2020
0$
#2025
b1110011011 !
b1110011011 )
b1110011011 *
b110 (
b11000110 +
b101110101011011101100000110011 -
1$
#2030
0$
#2035
b11000111 +
b101110101110101101100000001100 -
b1011000011 !
b1011000011 )
b1011000011 *
b111 (
1$
#2040
0$
#2045
b101111111 !
b101111111 )
b101111111 *
b1000 (
b11001000 +
b101110110000100111100010010101 -
1$
#2050
0$
#2055
b11001001 +
b101110110001001011010110010110 -
b0 !
b0 )
b0 *
b1001 (
1$
#2060
0$
#2065
b1111111010000001 !
b1111111010000001 )
b1111111010000001 *
b1010 (
b11001010 +
1$
#2070
0$
#2075
b11001011 +
b101011110010001111001010010111 -
b1111110100111101 !
b1111110100111101 )
b1111110100111101 *
b1011 (
1$
#2080
0$
#2085
b1111110001100101 !
b1111110001100101 )
b1111110001100101 *
b1100 (
b11001100 +
b100110010010101001001100100000 -
1$
#2090
0$
#2095
b11001101 +
b11111001000011001001011111001 -
b1111110000011000 !
b1111110000011000 )
b1111110000011000 *
b1101 (
1$
#2100
0$
